benchmark/__init__.py
benchmark/ackley.py
benchmark/griewank.py
benchmark/rastrigin.py
benchmark/sphere.py
examples/output_sample/custom/custom.py
oopoa/main.py
oopoa/commands/__init__.py
oopoa/commands/benchmark.py
oopoa/commands/plot.py
oopoa/core/__init__.py
oopoa/core/optimizer.py
oopoa/core/population.py
oopoa/plots/__init__.py
oopoa/plots/graph.py
oopoa-0.2.dist-info/licenses/LICENSE
tests/test_core.py
oopoa-0.2.dist-info/METADATA
oopoa-0.2.dist-info/WHEEL
oopoa-0.2.dist-info/entry_points.txt
oopoa-0.2.dist-info/top_level.txt
oopoa-0.2.dist-info/RECORD
