Metadata-Version: 2.4
Name: oopoa
Version: 0.2
Summary: OOPOA CLI Tool (Object-Oriented Programming Optimization Algorithm)
License-Expression: MIT
Project-URL: Homepage, https://github.com/LA-10/oop-optimizer
Project-URL: issues, https://github.com/LA-10/oop-optimizer/issues
Requires-Python: >=3.8
License-File: LICENSE
Requires-Dist: numpy
Requires-Dist: matplotlib
Requires-Dist: click
Requires-Dist: pandas
Requires-Dist: colorama
Dynamic: license-file
